passrack.py
passrack-0.1.6.dist-info/entry_points.txt
passrack-0.1.6.dist-info/LICENSE.md
passrack-0.1.6.dist-info/WHEEL
passrack-0.1.6.dist-info/METADATA
passrack-0.1.6.dist-info/RECORD
